swarmauri_certs_remote_ca/RemoteCaCertService.py
swarmauri_certs_remote_ca/__init__.py
swarmauri_certs_remote_ca-0.3.0.dev4.dist-info/LICENSE
swarmauri_certs_remote_ca-0.3.0.dev4.dist-info/METADATA
swarmauri_certs_remote_ca-0.3.0.dev4.dist-info/WHEEL
swarmauri_certs_remote_ca-0.3.0.dev4.dist-info/entry_points.txt
swarmauri_certs_remote_ca-0.3.0.dev4.dist-info/RECORD
