Metadata-Version: 2.3
Name: swarmauri_certs_remote_ca
Version: 0.3.0.dev4
Summary: Remote CA certificate service for Swarmauri
License: Apache-2.0
Author: Swarmauri
Author-email: opensource@swarmauri.com
Requires-Python: >=3.10,<3.13
Classifier: License :: OSI Approved :: Apache Software License
Classifier: Natural Language :: English
Classifier: Programming Language :: Python :: 3.10
Classifier: Programming Language :: Python :: 3.11
Classifier: Programming Language :: Python :: 3.12
Classifier: Programming Language :: Python :: 3.13
Classifier: Development Status :: 3 - Alpha
Classifier: Topic :: Security :: Cryptography
Classifier: Intended Audience :: Developers
Provides-Extra: parse
Requires-Dist: cryptography ; extra == "parse"
Requires-Dist: httpx
Requires-Dist: swarmauri_base
Requires-Dist: swarmauri_core
